LICENSE.md
MANIFEST.in
README.md
req.py
requirements.txt
setup.py
dwork/__init__.py
dwork.egg-info/PKG-INFO
dwork.egg-info/SOURCES.txt
dwork.egg-info/dependency_links.txt
dwork.egg-info/not-zip-safe
dwork.egg-info/top_level.txt
dwork/dataschema/__init__.py
dwork/dataschema/dataschema.py
dwork/dataset/__init__.py
dwork/dataset/attribute.py
dwork/dataset/dataset.py
dwork/dataset/pandas.py
dwork/language/__init__.py
dwork/language/comparison.py
dwork/language/expression.py
dwork/language/functions.py
dwork/language/operators.py
dwork/language/types.py
dwork/mechanisms/__init__.py
dwork/mechanisms/exponential.py
dwork/mechanisms/geometric.py
dwork/mechanisms/laplace.py
dwork/mechanisms/random.py
dwork_tests/__init__.py
dwork_tests/test_dataset.py
dwork_tests/test_expressions.py
dwork_tests/test_group_by.py
examples/__init__.py
examples/queries/__init__.py
examples/queries/dp_queries.py
examples/sampling/__init__.py
examples/sampling/randomized_sample.py