Metadata-Version: 2.1
Name: dwork
Version: 0.0.13
Summary: A Python toolkit for differentially private data science & analytics.
Home-page: https://github.com/kiprotect/dwork
Author: KIProtect GmbH
Author-email: dwork@kiprotect.com
License: BSD-3
Requires-Python: >=3.6
License-File: LICENSE.md
